hw_compat_matrix/__init__.py
hw_compat_matrix/loader.py
hw_compat_matrix/models.py
hw_compat_matrix/data/cuda_driver_matrix.yaml
hw_compat_matrix/data/gpu_name_aliases.yaml
hw_compat_matrix/data/nvidia_sm_map.yaml
hw_compat_matrix-0.3.0.dist-info/METADATA
hw_compat_matrix-0.3.0.dist-info/WHEEL
hw_compat_matrix-0.3.0.dist-info/licenses/LICENSE
hw_compat_matrix-0.3.0.dist-info/RECORD
