Metadata-Version: 2.4
Name: hw-compat-matrix
Version: 0.3.0
Summary: Canonical CUDA/GPU compatibility metadata for hardware compatibility checking
Project-URL: Homepage, https://github.com/ATTMOS/hw-compat-matrix
Project-URL: Repository, https://github.com/ATTMOS/hw-compat-matrix
Project-URL: Issues, https://github.com/ATTMOS/hw-compat-matrix/issues
Author-email: ATTMOS <support@attmos.com>
License-Expression: MIT
License-File: LICENSE
Keywords: compatibility,cuda,driver,gpu,hardware,nvidia
Classifier: Development Status :: 4 - Beta
Classifier: Intended Audience :: Developers
Classifier: License :: OSI Approved :: MIT License
Classifier: Operating System :: OS Independent
Classifier: Programming Language :: Python :: 3
Classifier: Programming Language :: Python :: 3.9
Classifier: Programming Language :: Python :: 3.10
Classifier: Programming Language :: Python :: 3.11
Classifier: Programming Language :: Python :: 3.12
Classifier: Programming Language :: Python :: 3.13
Classifier: Topic :: Scientific/Engineering
Classifier: Topic :: System :: Hardware
Requires-Python: >=3.9
Requires-Dist: pydantic>=2.0
Requires-Dist: pyyaml>=6.0
Provides-Extra: dev
Requires-Dist: jsonschema>=4.0; extra == 'dev'
Requires-Dist: pytest>=7.0; extra == 'dev'
